<?xml version="1.0" encoding="utf-8"?>
<ns3:financialActivityPlan2020 xsi:schemaLocation="http://bus.gov.ru/External/1 http://bus.gov.ru/public/schema/TFF-1.7.8.19/External.xsd" xmlns="http://bus.gov.ru/types/1" xmlns:ns2="http://bus.gov.ru/types/3" xmlns:ns4="http://bus.gov.ru/types/2" xmlns:ns3="http://bus.gov.ru/external/1" xmlns:xsi="http://www.w3.org/2001/XMLSchema-instance">
	<header>
		<id>729a037e-91ba-47d8-8ee6-7439c245f03d</id>
		<createDateTime>2020-11-09T15:51:50.519+03:00</createDateTime>
	</header>
	<ns3:body>
		<ns3:position>
			<positionId>f1184a19-2f6a-4ae6-bff8-a9a01fae7a31</positionId>
			<changeDate>2020-11-09T15:51:50.519+03:00</changeDate>
			<placer>
				<regNum>25301832</regNum>
				<fullName>МБОУ 'Гимназия № 1'</fullName>
				<inn>3819009080</inn>
				<kpp>385101001</kpp>
			</placer>
			<initiator>
				<regNum>25301832</regNum>
				<fullName>МБОУ 'Гимназия № 1'</fullName>
				<inn>3819009080</inn>
				<kpp>385101001</kpp>
			</initiator>
			<versionNumber>0</versionNumber>
			<ns2:financialYear>2020</ns2:financialYear>
			<ns2:planFirstYear>2021</ns2:planFirstYear>
			<ns2:planLastYear>2022</ns2:planLastYear>
			<ns2:generalData>
				<ns2:date>2010-11-30+03:00</ns2:date>
				<ns2:dateApprovel>2010-11-30+03:00</ns2:dateApprovel>
				<ns2:founderAuthority>
					<regNum>25304951</regNum>
					<inn>3819005092</inn>
					<kpp>385145003</kpp>
					<ns2:glavaCode>905</ns2:glavaCode>
				</ns2:founderAuthority>
				<ns2:okei>
					<code>383</code>
					<symbol>руб</symbol>
				</ns2:okei>
			</ns2:generalData>
			<ns2:planPaymentIndex>
				<ns2:name>Остаток средств на начало текущего финансового года 5</ns2:name>
				<ns2:lineCode>0001</ns2:lineCode>
				<ns2:manually>false</ns2:manually>
				<ns2:sum>
					<ns2:financialYearSum>1096009.41</ns2:financialYearSum>
					<ns2:planFirstYearSum>0</ns2:planFirstYearSum>
					<ns2:planLastYearSum>0</ns2:planLastYearSum>
					<ns2:autPlanYearSum>0</ns2:autPlanYearSum>
				</ns2:sum>
			</ns2:planPaymentIndex>
			<ns2:planPaymentIndex>
				<ns2:name>Остаток средств на конец текущего финансового года 5</ns2:name>
				<ns2:lineCode>0002</ns2:lineCode>
				<ns2:manually>false</ns2:manually>
				<ns2:sum>
					<ns2:financialYearSum>-7.45058059e-09</ns2:financialYearSum>
					<ns2:planFirstYearSum>0</ns2:planFirstYearSum>
					<ns2:planLastYearSum>0</ns2:planLastYearSum>
					<ns2:autPlanYearSum>0</ns2:autPlanYearSum>
				</ns2:sum>
			</ns2:planPaymentIndex>
			<ns2:planPaymentIndex>
				<ns2:name>Доходы всего</ns2:name>
				<ns2:lineCode>1000</ns2:lineCode>
				<ns2:manually>false</ns2:manually>
				<ns2:analyticCode>100</ns2:analyticCode>
				<ns2:sum>
					<ns2:financialYearSum>46516591.58</ns2:financialYearSum>
					<ns2:planFirstYearSum>0</ns2:planFirstYearSum>
					<ns2:planLastYearSum>0</ns2:planLastYearSum>
					<ns2:autPlanYearSum>0</ns2:autPlanYearSum>
				</ns2:sum>
			</ns2:planPaymentIndex>
			<ns2:planPaymentIndex>
				<ns2:name> в том числе доходы от собственности всего в том числе</ns2:name>
				<ns2:lineCode>1100</ns2:lineCode>
				<ns2:manually>false</ns2:manually>
				<ns2:sum>
					<ns2:financialYearSum>0</ns2:financialYearSum>
					<ns2:planFirstYearSum>0</ns2:planFirstYearSum>
					<ns2:planLastYearSum>0</ns2:planLastYearSum>
					<ns2:autPlanYearSum>0</ns2:autPlanYearSum>
				</ns2:sum>
			</ns2:planPaymentIndex>
			<ns2:planPaymentIndex>
				<ns2:name> доходы от оказания услуг работ компенсации затрат учреждений всего</ns2:name>
				<ns2:lineCode>1200</ns2:lineCode>
				<ns2:manually>false</ns2:manually>
				<ns2:analyticCode>130</ns2:analyticCode>
				<ns2:sum>
					<ns2:financialYearSum>39671169.31</ns2:financialYearSum>
					<ns2:planFirstYearSum>0</ns2:planFirstYearSum>
					<ns2:planLastYearSum>0</ns2:planLastYearSum>
					<ns2:autPlanYearSum>0</ns2:autPlanYearSum>
				</ns2:sum>
			</ns2:planPaymentIndex>
			<ns2:planPaymentIndex>
				<ns2:name> в том числе субсидии на финансовое обеспечение выполнения государственного муниципального задания за счет средств бюджета публичноправового образования создавшего учреждение</ns2:name>
				<ns2:lineCode>1210</ns2:lineCode>
				<ns2:manually>false</ns2:manually>
				<ns2:analyticCode>131</ns2:analyticCode>
				<ns2:sum>
					<ns2:financialYearSum>39671169.31</ns2:financialYearSum>
					<ns2:planFirstYearSum>0</ns2:planFirstYearSum>
					<ns2:planLastYearSum>0</ns2:planLastYearSum>
					<ns2:autPlanYearSum>0</ns2:autPlanYearSum>
				</ns2:sum>
			</ns2:planPaymentIndex>
			<ns2:planPaymentIndex>
				<ns2:name> субсидии на финансовое обеспечение выполнения  государственного задания за счет средств бюджета  Федерального фонда обязательного медицинского  страхования</ns2:name>
				<ns2:lineCode>1220</ns2:lineCode>
				<ns2:manually>false</ns2:manually>
				<ns2:sum>
					<ns2:financialYearSum>0</ns2:financialYearSum>
					<ns2:planFirstYearSum>0</ns2:planFirstYearSum>
					<ns2:planLastYearSum>0</ns2:planLastYearSum>
					<ns2:autPlanYearSum>0</ns2:autPlanYearSum>
				</ns2:sum>
			</ns2:planPaymentIndex>
			<ns2:planPaymentIndex>
				<ns2:name> Доходы от оказания платных услуг работ</ns2:name>
				<ns2:lineCode></ns2:lineCode>
				<ns2:manually>false</ns2:manually>
				<ns2:analyticCode>131</ns2:analyticCode>
				<ns2:sum>
					<ns2:financialYearSum>39671169.31</ns2:financialYearSum>
					<ns2:planFirstYearSum>0</ns2:planFirstYearSum>
					<ns2:planLastYearSum>0</ns2:planLastYearSum>
					<ns2:autPlanYearSum>0</ns2:autPlanYearSum>
				</ns2:sum>
			</ns2:planPaymentIndex>
			<ns2:planPaymentIndex>
				<ns2:name> доходы от штрафов пеней иных сумм принудительного изъятия всего в том числе</ns2:name>
				<ns2:lineCode>1300</ns2:lineCode>
				<ns2:manually>false</ns2:manually>
				<ns2:sum>
					<ns2:financialYearSum>0</ns2:financialYearSum>
					<ns2:planFirstYearSum>0</ns2:planFirstYearSum>
					<ns2:planLastYearSum>0</ns2:planLastYearSum>
					<ns2:autPlanYearSum>0</ns2:autPlanYearSum>
				</ns2:sum>
			</ns2:planPaymentIndex>
			<ns2:planPaymentIndex>
				<ns2:name> безвозмездные денежные поступления всего в том числе</ns2:name>
				<ns2:lineCode>1400</ns2:lineCode>
				<ns2:manually>false</ns2:manually>
				<ns2:analyticCode>150</ns2:analyticCode>
				<ns2:sum>
					<ns2:financialYearSum>6845422.27</ns2:financialYearSum>
					<ns2:planFirstYearSum>0</ns2:planFirstYearSum>
					<ns2:planLastYearSum>0</ns2:planLastYearSum>
					<ns2:autPlanYearSum>0</ns2:autPlanYearSum>
				</ns2:sum>
			</ns2:planPaymentIndex>
			<ns2:planPaymentIndex>
				<ns2:name> Поступления текущего характера бюджетным и автономным учреждениям от сектора государственного управления</ns2:name>
				<ns2:lineCode>1410</ns2:lineCode>
				<ns2:manually>false</ns2:manually>
				<ns2:analyticCode>152</ns2:analyticCode>
				<ns2:sum>
					<ns2:financialYearSum>6756941.95</ns2:financialYearSum>
					<ns2:planFirstYearSum>0</ns2:planFirstYearSum>
					<ns2:planLastYearSum>0</ns2:planLastYearSum>
					<ns2:autPlanYearSum>0</ns2:autPlanYearSum>
				</ns2:sum>
			</ns2:planPaymentIndex>
			<ns2:planPaymentIndex>
				<ns2:name> Поступления текущего характера от иных резидентов за исключением сектора государственного управления и организаций государственного сектора</ns2:name>
				<ns2:lineCode></ns2:lineCode>
				<ns2:manually>false</ns2:manually>
				<ns2:analyticCode>155</ns2:analyticCode>
				<ns2:sum>
					<ns2:financialYearSum>88480.32</ns2:financialYearSum>
					<ns2:planFirstYearSum>0</ns2:planFirstYearSum>
					<ns2:planLastYearSum>0</ns2:planLastYearSum>
					<ns2:autPlanYearSum>0</ns2:autPlanYearSum>
				</ns2:sum>
			</ns2:planPaymentIndex>
			<ns2:planPaymentIndex>
				<ns2:name> прочие доходы всего</ns2:name>
				<ns2:lineCode>1500</ns2:lineCode>
				<ns2:manually>false</ns2:manually>
				<ns2:sum>
					<ns2:financialYearSum>0</ns2:financialYearSum>
					<ns2:planFirstYearSum>0</ns2:planFirstYearSum>
					<ns2:planLastYearSum>0</ns2:planLastYearSum>
					<ns2:autPlanYearSum>0</ns2:autPlanYearSum>
				</ns2:sum>
			</ns2:planPaymentIndex>
			<ns2:planPaymentIndex>
				<ns2:name> в том числе целевые субсидии</ns2:name>
				<ns2:lineCode>1510</ns2:lineCode>
				<ns2:manually>false</ns2:manually>
				<ns2:sum>
					<ns2:financialYearSum>0</ns2:financialYearSum>
					<ns2:planFirstYearSum>0</ns2:planFirstYearSum>
					<ns2:planLastYearSum>0</ns2:planLastYearSum>
					<ns2:autPlanYearSum>0</ns2:autPlanYearSum>
				</ns2:sum>
			</ns2:planPaymentIndex>
			<ns2:planPaymentIndex>
				<ns2:name> субсидии на осуществление капитальных вложений</ns2:name>
				<ns2:lineCode>1520</ns2:lineCode>
				<ns2:manually>false</ns2:manually>
				<ns2:sum>
					<ns2:financialYearSum>0</ns2:financialYearSum>
					<ns2:planFirstYearSum>0</ns2:planFirstYearSum>
					<ns2:planLastYearSum>0</ns2:planLastYearSum>
					<ns2:autPlanYearSum>0</ns2:autPlanYearSum>
				</ns2:sum>
			</ns2:planPaymentIndex>
			<ns2:planPaymentIndex>
				<ns2:name> доходы от операций с активами всего  в том числе</ns2:name>
				<ns2:lineCode>1900</ns2:lineCode>
				<ns2:manually>false</ns2:manually>
				<ns2:sum>
					<ns2:financialYearSum>0</ns2:financialYearSum>
					<ns2:planFirstYearSum>0</ns2:planFirstYearSum>
					<ns2:planLastYearSum>0</ns2:planLastYearSum>
					<ns2:autPlanYearSum>0</ns2:autPlanYearSum>
				</ns2:sum>
			</ns2:planPaymentIndex>
			<ns2:planPaymentIndex>
				<ns2:name> прочие поступления всего 6</ns2:name>
				<ns2:lineCode>1980</ns2:lineCode>
				<ns2:manually>false</ns2:manually>
				<ns2:sum>
					<ns2:financialYearSum>0</ns2:financialYearSum>
					<ns2:planFirstYearSum>0</ns2:planFirstYearSum>
					<ns2:planLastYearSum>0</ns2:planLastYearSum>
					<ns2:autPlanYearSum>0</ns2:autPlanYearSum>
				</ns2:sum>
			</ns2:planPaymentIndex>
			<ns2:planPaymentIndex>
				<ns2:name> из них увеличение остатков денежных средств за счет возврата  дебиторской задолженности прошлых лет</ns2:name>
				<ns2:lineCode>1981</ns2:lineCode>
				<ns2:manually>false</ns2:manually>
				<ns2:sum>
					<ns2:financialYearSum>0</ns2:financialYearSum>
					<ns2:planFirstYearSum>0</ns2:planFirstYearSum>
					<ns2:planLastYearSum>0</ns2:planLastYearSum>
				</ns2:sum>
			</ns2:planPaymentIndex>
			<ns2:planPaymentIndex>
				<ns2:name>Расходы всего</ns2:name>
				<ns2:lineCode>2000</ns2:lineCode>
				<ns2:manually>false</ns2:manually>
				<ns2:sum>
					<ns2:financialYearSum>47612600.99</ns2:financialYearSum>
					<ns2:planFirstYearSum>42720602.71</ns2:planFirstYearSum>
					<ns2:planLastYearSum>42273902.71</ns2:planLastYearSum>
					<ns2:autPlanYearSum>0</ns2:autPlanYearSum>
				</ns2:sum>
			</ns2:planPaymentIndex>
			<ns2:planPaymentIndex>
				<ns2:name> в том числе на выплаты персоналу всего</ns2:name>
				<ns2:lineCode>2100</ns2:lineCode>
				<ns2:manually>false</ns2:manually>
				<ns2:sum>
					<ns2:financialYearSum>36560271.89</ns2:financialYearSum>
					<ns2:planFirstYearSum>34653992.93</ns2:planFirstYearSum>
					<ns2:planLastYearSum>34653992.93</ns2:planLastYearSum>
				</ns2:sum>
			</ns2:planPaymentIndex>
			<ns2:planPaymentIndex>
				<ns2:name> в том числе оплата труда</ns2:name>
				<ns2:lineCode>2110</ns2:lineCode>
				<ns2:manually>false</ns2:manually>
				<ns2:sum>
					<ns2:financialYearSum>28143426.82</ns2:financialYearSum>
					<ns2:planFirstYearSum>26691585.97</ns2:planFirstYearSum>
					<ns2:planLastYearSum>26691585.97</ns2:planLastYearSum>
				</ns2:sum>
			</ns2:planPaymentIndex>
			<ns2:planPaymentIndex>
				<ns2:name> Заработная плата</ns2:name>
				<ns2:lineCode></ns2:lineCode>
				<ns2:manually>false</ns2:manually>
				<ns2:analyticCode>211</ns2:analyticCode>
				<ns2:sum>
					<ns2:financialYearSum>28053426.82</ns2:financialYearSum>
					<ns2:planFirstYearSum>26691585.97</ns2:planFirstYearSum>
					<ns2:planLastYearSum>26691585.97</ns2:planLastYearSum>
				</ns2:sum>
			</ns2:planPaymentIndex>
			<ns2:planPaymentIndex>
				<ns2:name> Социальные пособия и компенсации персоналу в денежной форме</ns2:name>
				<ns2:lineCode></ns2:lineCode>
				<ns2:manually>false</ns2:manually>
				<ns2:analyticCode>266</ns2:analyticCode>
				<ns2:sum>
					<ns2:financialYearSum>90000.0</ns2:financialYearSum>
					<ns2:planFirstYearSum>0</ns2:planFirstYearSum>
					<ns2:planLastYearSum>0</ns2:planLastYearSum>
					<ns2:autPlanYearSum>0</ns2:autPlanYearSum>
				</ns2:sum>
			</ns2:planPaymentIndex>
			<ns2:planPaymentIndex>
				<ns2:name> прочие выплаты персоналу в том числе компенсационного  характера</ns2:name>
				<ns2:lineCode>2120</ns2:lineCode>
				<ns2:manually>false</ns2:manually>
				<ns2:sum>
					<ns2:financialYearSum>0</ns2:financialYearSum>
					<ns2:planFirstYearSum>0</ns2:planFirstYearSum>
					<ns2:planLastYearSum>0</ns2:planLastYearSum>
				</ns2:sum>
			</ns2:planPaymentIndex>
			<ns2:planPaymentIndex>
				<ns2:name> иные выплаты за исключением фонда оплаты труда учреждения для выполнения отдельных полномочий</ns2:name>
				<ns2:lineCode>2130</ns2:lineCode>
				<ns2:manually>false</ns2:manually>
				<ns2:sum>
					<ns2:financialYearSum>0</ns2:financialYearSum>
					<ns2:planFirstYearSum>0</ns2:planFirstYearSum>
					<ns2:planLastYearSum>0</ns2:planLastYearSum>
				</ns2:sum>
			</ns2:planPaymentIndex>
			<ns2:planPaymentIndex>
				<ns2:name> взносы по обязательному социальному страхованию на выплаты по оплате труда работников и иные выплаты работникам учреждений всего</ns2:name>
				<ns2:lineCode>2140</ns2:lineCode>
				<ns2:manually>false</ns2:manually>
				<ns2:sum>
					<ns2:financialYearSum>8416845.07</ns2:financialYearSum>
					<ns2:planFirstYearSum>7962406.96</ns2:planFirstYearSum>
					<ns2:planLastYearSum>7962406.96</ns2:planLastYearSum>
				</ns2:sum>
			</ns2:planPaymentIndex>
			<ns2:planPaymentIndex>
				<ns2:name> в том числе на выплаты по оплате труда</ns2:name>
				<ns2:lineCode>2141</ns2:lineCode>
				<ns2:manually>false</ns2:manually>
				<ns2:analyticCode>213</ns2:analyticCode>
				<ns2:sum>
					<ns2:financialYearSum>8416845.07</ns2:financialYearSum>
					<ns2:planFirstYearSum>7962406.96</ns2:planFirstYearSum>
					<ns2:planLastYearSum>7962406.96</ns2:planLastYearSum>
				</ns2:sum>
			</ns2:planPaymentIndex>
			<ns2:planPaymentIndex>
				<ns2:name> на иные выплаты работникам</ns2:name>
				<ns2:lineCode>2142</ns2:lineCode>
				<ns2:manually>false</ns2:manually>
				<ns2:sum>
					<ns2:financialYearSum>0</ns2:financialYearSum>
					<ns2:planFirstYearSum>0</ns2:planFirstYearSum>
					<ns2:planLastYearSum>0</ns2:planLastYearSum>
				</ns2:sum>
			</ns2:planPaymentIndex>
			<ns2:planPaymentIndex>
				<ns2:name> денежное довольствие военнослужащих и сотрудников имеющих специальные звания</ns2:name>
				<ns2:lineCode>2150</ns2:lineCode>
				<ns2:manually>false</ns2:manually>
				<ns2:sum>
					<ns2:financialYearSum>0</ns2:financialYearSum>
					<ns2:planFirstYearSum>0</ns2:planFirstYearSum>
					<ns2:planLastYearSum>0</ns2:planLastYearSum>
				</ns2:sum>
			</ns2:planPaymentIndex>
			<ns2:planPaymentIndex>
				<ns2:name> иные выплаты военнослужащим и сотрудникам имеющим специальные звания</ns2:name>
				<ns2:lineCode>2160</ns2:lineCode>
				<ns2:manually>false</ns2:manually>
				<ns2:sum>
					<ns2:financialYearSum>0</ns2:financialYearSum>
					<ns2:planFirstYearSum>0</ns2:planFirstYearSum>
					<ns2:planLastYearSum>0</ns2:planLastYearSum>
				</ns2:sum>
			</ns2:planPaymentIndex>
			<ns2:planPaymentIndex>
				<ns2:name> страховые взносы на обязательное социальное страхование в части выплат персоналу подлежащих обложению страховыми взносами</ns2:name>
				<ns2:lineCode>2170</ns2:lineCode>
				<ns2:manually>false</ns2:manually>
				<ns2:sum>
					<ns2:financialYearSum>0</ns2:financialYearSum>
					<ns2:planFirstYearSum>0</ns2:planFirstYearSum>
					<ns2:planLastYearSum>0</ns2:planLastYearSum>
				</ns2:sum>
			</ns2:planPaymentIndex>
			<ns2:planPaymentIndex>
				<ns2:name> в том числе на оплату труда стажеров</ns2:name>
				<ns2:lineCode>2171</ns2:lineCode>
				<ns2:manually>false</ns2:manually>
				<ns2:sum>
					<ns2:financialYearSum>0</ns2:financialYearSum>
					<ns2:planFirstYearSum>0</ns2:planFirstYearSum>
					<ns2:planLastYearSum>0</ns2:planLastYearSum>
				</ns2:sum>
			</ns2:planPaymentIndex>
			<ns2:planPaymentIndex>
				<ns2:name> на иные выплаты гражданским лицам денежное содержание</ns2:name>
				<ns2:lineCode>2172</ns2:lineCode>
				<ns2:manually>false</ns2:manually>
				<ns2:sum>
					<ns2:financialYearSum>0</ns2:financialYearSum>
					<ns2:planFirstYearSum>0</ns2:planFirstYearSum>
					<ns2:planLastYearSum>0</ns2:planLastYearSum>
				</ns2:sum>
			</ns2:planPaymentIndex>
			<ns2:planPaymentIndex>
				<ns2:name> социальные и иные выплаты населению всего</ns2:name>
				<ns2:lineCode>2200</ns2:lineCode>
				<ns2:manually>false</ns2:manually>
				<ns2:sum>
					<ns2:financialYearSum>0</ns2:financialYearSum>
					<ns2:planFirstYearSum>0</ns2:planFirstYearSum>
					<ns2:planLastYearSum>0</ns2:planLastYearSum>
				</ns2:sum>
			</ns2:planPaymentIndex>
			<ns2:planPaymentIndex>
				<ns2:name> в том числе социальные выплаты гражданам кроме публичных нормативных социальных выплат</ns2:name>
				<ns2:lineCode>2210</ns2:lineCode>
				<ns2:manually>false</ns2:manually>
				<ns2:sum>
					<ns2:financialYearSum>0</ns2:financialYearSum>
					<ns2:planFirstYearSum>0</ns2:planFirstYearSum>
					<ns2:planLastYearSum>0</ns2:planLastYearSum>
				</ns2:sum>
			</ns2:planPaymentIndex>
			<ns2:planPaymentIndex>
				<ns2:name> из них пособия компенсации и иные социальные выплаты гражданам кроме публичных нормативных обязательств</ns2:name>
				<ns2:lineCode>2211</ns2:lineCode>
				<ns2:manually>false</ns2:manually>
				<ns2:sum>
					<ns2:financialYearSum>0</ns2:financialYearSum>
					<ns2:planFirstYearSum>0</ns2:planFirstYearSum>
					<ns2:planLastYearSum>0</ns2:planLastYearSum>
				</ns2:sum>
			</ns2:planPaymentIndex>
			<ns2:planPaymentIndex>
				<ns2:name> выплата стипендий осуществление иных расходов  на социальную поддержку обучающихся за счет средств стипендиального фонда </ns2:name>
				<ns2:lineCode>2220</ns2:lineCode>
				<ns2:manually>false</ns2:manually>
				<ns2:sum>
					<ns2:financialYearSum>0</ns2:financialYearSum>
					<ns2:planFirstYearSum>0</ns2:planFirstYearSum>
					<ns2:planLastYearSum>0</ns2:planLastYearSum>
				</ns2:sum>
			</ns2:planPaymentIndex>
			<ns2:planPaymentIndex>
				<ns2:name> на премирование физических лиц за достижения в области культуры искусства образования науки и техники  а также на предоставление грантов с целью поддержки проектов в области науки культуры и искусства</ns2:name>
				<ns2:lineCode>2230</ns2:lineCode>
				<ns2:manually>false</ns2:manually>
				<ns2:sum>
					<ns2:financialYearSum>0</ns2:financialYearSum>
					<ns2:planFirstYearSum>0</ns2:planFirstYearSum>
					<ns2:planLastYearSum>0</ns2:planLastYearSum>
				</ns2:sum>
			</ns2:planPaymentIndex>
			<ns2:planPaymentIndex>
				<ns2:name> социальное обеспечение детейсирот и детей  оставшихся без попечения родителей</ns2:name>
				<ns2:lineCode>2240</ns2:lineCode>
				<ns2:manually>false</ns2:manually>
				<ns2:sum>
					<ns2:financialYearSum>0</ns2:financialYearSum>
					<ns2:planFirstYearSum>0</ns2:planFirstYearSum>
					<ns2:planLastYearSum>0</ns2:planLastYearSum>
				</ns2:sum>
			</ns2:planPaymentIndex>
			<ns2:planPaymentIndex>
				<ns2:name> уплата налогов сборов и иных платежей всего</ns2:name>
				<ns2:lineCode>2300</ns2:lineCode>
				<ns2:manually>false</ns2:manually>
				<ns2:sum>
					<ns2:financialYearSum>310050.0</ns2:financialYearSum>
					<ns2:planFirstYearSum>151858.82</ns2:planFirstYearSum>
					<ns2:planLastYearSum>151858.82</ns2:planLastYearSum>
				</ns2:sum>
			</ns2:planPaymentIndex>
			<ns2:planPaymentIndex>
				<ns2:name> из них налог на имущество организаций и земельный налог</ns2:name>
				<ns2:lineCode>2310</ns2:lineCode>
				<ns2:manually>false</ns2:manually>
				<ns2:analyticCode>291</ns2:analyticCode>
				<ns2:sum>
					<ns2:financialYearSum>310050.0</ns2:financialYearSum>
					<ns2:planFirstYearSum>151858.82</ns2:planFirstYearSum>
					<ns2:planLastYearSum>151858.82</ns2:planLastYearSum>
				</ns2:sum>
			</ns2:planPaymentIndex>
			<ns2:planPaymentIndex>
				<ns2:name> иные налоги включаемые в состав расходов в бюджеты бюджетной системы Российской Федерации а также государственная пошлина</ns2:name>
				<ns2:lineCode>2320</ns2:lineCode>
				<ns2:manually>false</ns2:manually>
				<ns2:sum>
					<ns2:financialYearSum>0</ns2:financialYearSum>
					<ns2:planFirstYearSum>0</ns2:planFirstYearSum>
					<ns2:planLastYearSum>0</ns2:planLastYearSum>
				</ns2:sum>
			</ns2:planPaymentIndex>
			<ns2:planPaymentIndex>
				<ns2:name> уплата штрафов в том числе административных пеней иных платежей</ns2:name>
				<ns2:lineCode>2330</ns2:lineCode>
				<ns2:manually>false</ns2:manually>
				<ns2:sum>
					<ns2:financialYearSum>0</ns2:financialYearSum>
					<ns2:planFirstYearSum>0</ns2:planFirstYearSum>
					<ns2:planLastYearSum>0</ns2:planLastYearSum>
				</ns2:sum>
			</ns2:planPaymentIndex>
			<ns2:planPaymentIndex>
				<ns2:name> безвозмездные перечисления организациям и физическим лицам всего</ns2:name>
				<ns2:lineCode>2400</ns2:lineCode>
				<ns2:manually>false</ns2:manually>
				<ns2:sum>
					<ns2:financialYearSum>0</ns2:financialYearSum>
					<ns2:planFirstYearSum>0</ns2:planFirstYearSum>
					<ns2:planLastYearSum>0</ns2:planLastYearSum>
				</ns2:sum>
			</ns2:planPaymentIndex>
			<ns2:planPaymentIndex>
				<ns2:name> из них гранты предоставляемые другим организациям и физическим лицам</ns2:name>
				<ns2:lineCode>2410</ns2:lineCode>
				<ns2:manually>false</ns2:manually>
				<ns2:sum>
					<ns2:financialYearSum>0</ns2:financialYearSum>
					<ns2:planFirstYearSum>0</ns2:planFirstYearSum>
					<ns2:planLastYearSum>0</ns2:planLastYearSum>
				</ns2:sum>
			</ns2:planPaymentIndex>
			<ns2:planPaymentIndex>
				<ns2:name> взносы в международные организации</ns2:name>
				<ns2:lineCode>2420</ns2:lineCode>
				<ns2:manually>false</ns2:manually>
				<ns2:sum>
					<ns2:financialYearSum>0</ns2:financialYearSum>
					<ns2:planFirstYearSum>0</ns2:planFirstYearSum>
					<ns2:planLastYearSum>0</ns2:planLastYearSum>
				</ns2:sum>
			</ns2:planPaymentIndex>
			<ns2:planPaymentIndex>
				<ns2:name> платежи в целях обеспечения реализации соглашений с правительствами иностранных государств и международными организациями</ns2:name>
				<ns2:lineCode>2430</ns2:lineCode>
				<ns2:manually>false</ns2:manually>
				<ns2:sum>
					<ns2:financialYearSum>0</ns2:financialYearSum>
					<ns2:planFirstYearSum>0</ns2:planFirstYearSum>
					<ns2:planLastYearSum>0</ns2:planLastYearSum>
				</ns2:sum>
			</ns2:planPaymentIndex>
			<ns2:planPaymentIndex>
				<ns2:name> прочие выплаты кроме выплат на закупку товаров работ услуг</ns2:name>
				<ns2:lineCode>2500</ns2:lineCode>
				<ns2:manually>false</ns2:manually>
				<ns2:sum>
					<ns2:financialYearSum>0</ns2:financialYearSum>
					<ns2:planFirstYearSum>0</ns2:planFirstYearSum>
					<ns2:planLastYearSum>0</ns2:planLastYearSum>
				</ns2:sum>
			</ns2:planPaymentIndex>
			<ns2:planPaymentIndex>
				<ns2:name> исполнение судебных актов Российской Федерации и  мировых соглашений по возмещению вреда причиненного в результате деятельности учреждения</ns2:name>
				<ns2:lineCode>2520</ns2:lineCode>
				<ns2:manually>false</ns2:manually>
				<ns2:sum>
					<ns2:financialYearSum>0</ns2:financialYearSum>
					<ns2:planFirstYearSum>0</ns2:planFirstYearSum>
					<ns2:planLastYearSum>0</ns2:planLastYearSum>
				</ns2:sum>
			</ns2:planPaymentIndex>
			<ns2:planPaymentIndex>
				<ns2:name> расходы на закупку товаров работ услуг всего 7</ns2:name>
				<ns2:lineCode>2600</ns2:lineCode>
				<ns2:manually>false</ns2:manually>
				<ns2:sum>
					<ns2:financialYearSum>10742279.1</ns2:financialYearSum>
					<ns2:planFirstYearSum>7914750.96</ns2:planFirstYearSum>
					<ns2:planLastYearSum>7468050.96</ns2:planLastYearSum>
					<ns2:autPlanYearSum>0</ns2:autPlanYearSum>
				</ns2:sum>
			</ns2:planPaymentIndex>
			<ns2:planPaymentIndex>
				<ns2:name> в том числе закупку научноисследовательских и опытно конструкторских работ</ns2:name>
				<ns2:lineCode>2610</ns2:lineCode>
				<ns2:manually>false</ns2:manually>
				<ns2:sum>
					<ns2:financialYearSum>0</ns2:financialYearSum>
					<ns2:planFirstYearSum>0</ns2:planFirstYearSum>
					<ns2:planLastYearSum>0</ns2:planLastYearSum>
					<ns2:autPlanYearSum>0</ns2:autPlanYearSum>
				</ns2:sum>
			</ns2:planPaymentIndex>
			<ns2:planPaymentIndex>
				<ns2:name> закупку товаров работ услуг в сфере информационно коммуникационных технологий</ns2:name>
				<ns2:lineCode>2620</ns2:lineCode>
				<ns2:manually>false</ns2:manually>
				<ns2:sum>
					<ns2:financialYearSum>0</ns2:financialYearSum>
					<ns2:planFirstYearSum>0</ns2:planFirstYearSum>
					<ns2:planLastYearSum>0</ns2:planLastYearSum>
					<ns2:autPlanYearSum>0</ns2:autPlanYearSum>
				</ns2:sum>
			</ns2:planPaymentIndex>
			<ns2:planPaymentIndex>
				<ns2:name> закупку товаров работ услуг в целях капитального ремонта государственного муниципального имущества</ns2:name>
				<ns2:lineCode>2630</ns2:lineCode>
				<ns2:manually>false</ns2:manually>
				<ns2:sum>
					<ns2:financialYearSum>845579.58</ns2:financialYearSum>
					<ns2:planFirstYearSum>446700.0</ns2:planFirstYearSum>
					<ns2:planLastYearSum>0</ns2:planLastYearSum>
					<ns2:autPlanYearSum>0</ns2:autPlanYearSum>
				</ns2:sum>
			</ns2:planPaymentIndex>
			<ns2:planPaymentIndex>
				<ns2:name> прочую закупку товаров работ и услуг всего из них</ns2:name>
				<ns2:lineCode>2640</ns2:lineCode>
				<ns2:manually>false</ns2:manually>
				<ns2:sum>
					<ns2:financialYearSum>9896699.52</ns2:financialYearSum>
					<ns2:planFirstYearSum>7468050.96</ns2:planFirstYearSum>
					<ns2:planLastYearSum>7468050.96</ns2:planLastYearSum>
					<ns2:autPlanYearSum>0</ns2:autPlanYearSum>
				</ns2:sum>
			</ns2:planPaymentIndex>
			<ns2:planPaymentIndex>
				<ns2:name> Услуги связи</ns2:name>
				<ns2:lineCode></ns2:lineCode>
				<ns2:manually>false</ns2:manually>
				<ns2:analyticCode>221</ns2:analyticCode>
				<ns2:sum>
					<ns2:financialYearSum>22843.2</ns2:financialYearSum>
					<ns2:planFirstYearSum>22843.2</ns2:planFirstYearSum>
					<ns2:planLastYearSum>22843.2</ns2:planLastYearSum>
					<ns2:autPlanYearSum>0</ns2:autPlanYearSum>
				</ns2:sum>
			</ns2:planPaymentIndex>
			<ns2:planPaymentIndex>
				<ns2:name> Коммунальные услуги</ns2:name>
				<ns2:lineCode></ns2:lineCode>
				<ns2:manually>false</ns2:manually>
				<ns2:analyticCode>223</ns2:analyticCode>
				<ns2:sum>
					<ns2:financialYearSum>1587774.19</ns2:financialYearSum>
					<ns2:planFirstYearSum>1800538.9</ns2:planFirstYearSum>
					<ns2:planLastYearSum>1800538.9</ns2:planLastYearSum>
					<ns2:autPlanYearSum>0</ns2:autPlanYearSum>
				</ns2:sum>
			</ns2:planPaymentIndex>
			<ns2:planPaymentIndex>
				<ns2:name> Работы услуги по содержанию имущества</ns2:name>
				<ns2:lineCode></ns2:lineCode>
				<ns2:manually>false</ns2:manually>
				<ns2:analyticCode>225</ns2:analyticCode>
				<ns2:sum>
					<ns2:financialYearSum>664586.3</ns2:financialYearSum>
					<ns2:planFirstYearSum>673896.27</ns2:planFirstYearSum>
					<ns2:planLastYearSum>673896.27</ns2:planLastYearSum>
					<ns2:autPlanYearSum>0</ns2:autPlanYearSum>
				</ns2:sum>
			</ns2:planPaymentIndex>
			<ns2:planPaymentIndex>
				<ns2:name> Прочие работы услуги</ns2:name>
				<ns2:lineCode></ns2:lineCode>
				<ns2:manually>false</ns2:manually>
				<ns2:analyticCode>226</ns2:analyticCode>
				<ns2:sum>
					<ns2:financialYearSum>5553817.66</ns2:financialYearSum>
					<ns2:planFirstYearSum>3336770.34</ns2:planFirstYearSum>
					<ns2:planLastYearSum>3336770.34</ns2:planLastYearSum>
					<ns2:autPlanYearSum>0</ns2:autPlanYearSum>
				</ns2:sum>
			</ns2:planPaymentIndex>
			<ns2:planPaymentIndex>
				<ns2:name> Увеличение стоимости основных средств</ns2:name>
				<ns2:lineCode></ns2:lineCode>
				<ns2:manually>false</ns2:manually>
				<ns2:analyticCode>310</ns2:analyticCode>
				<ns2:sum>
					<ns2:financialYearSum>1486816.7</ns2:financialYearSum>
					<ns2:planFirstYearSum>1394723.55</ns2:planFirstYearSum>
					<ns2:planLastYearSum>1394723.55</ns2:planLastYearSum>
					<ns2:autPlanYearSum>0</ns2:autPlanYearSum>
				</ns2:sum>
			</ns2:planPaymentIndex>
			<ns2:planPaymentIndex>
				<ns2:name> Увеличение стоимости лекарственных препаратов и материалов применяемых в медицинских целях</ns2:name>
				<ns2:lineCode></ns2:lineCode>
				<ns2:manually>false</ns2:manually>
				<ns2:analyticCode>341</ns2:analyticCode>
				<ns2:sum>
					<ns2:financialYearSum>10803.69</ns2:financialYearSum>
					<ns2:planFirstYearSum>10803.69</ns2:planFirstYearSum>
					<ns2:planLastYearSum>10803.69</ns2:planLastYearSum>
					<ns2:autPlanYearSum>0</ns2:autPlanYearSum>
				</ns2:sum>
			</ns2:planPaymentIndex>
			<ns2:planPaymentIndex>
				<ns2:name> Увеличение стоимости строительных материалов</ns2:name>
				<ns2:lineCode></ns2:lineCode>
				<ns2:manually>false</ns2:manually>
				<ns2:analyticCode>344</ns2:analyticCode>
				<ns2:sum>
					<ns2:financialYearSum>356272.77</ns2:financialYearSum>
					<ns2:planFirstYearSum>0</ns2:planFirstYearSum>
					<ns2:planLastYearSum>0</ns2:planLastYearSum>
					<ns2:autPlanYearSum>0</ns2:autPlanYearSum>
				</ns2:sum>
			</ns2:planPaymentIndex>
			<ns2:planPaymentIndex>
				<ns2:name> Увеличение стоимости прочих материальных запасов</ns2:name>
				<ns2:lineCode></ns2:lineCode>
				<ns2:manually>false</ns2:manually>
				<ns2:analyticCode>346</ns2:analyticCode>
				<ns2:sum>
					<ns2:financialYearSum>194706.01</ns2:financialYearSum>
					<ns2:planFirstYearSum>209396.01</ns2:planFirstYearSum>
					<ns2:planLastYearSum>209396.01</ns2:planLastYearSum>
					<ns2:autPlanYearSum>0</ns2:autPlanYearSum>
				</ns2:sum>
			</ns2:planPaymentIndex>
			<ns2:planPaymentIndex>
				<ns2:name> Увеличение стоимости прочих материальных запасов однократного применения</ns2:name>
				<ns2:lineCode></ns2:lineCode>
				<ns2:manually>false</ns2:manually>
				<ns2:analyticCode>349</ns2:analyticCode>
				<ns2:sum>
					<ns2:financialYearSum>19079.0</ns2:financialYearSum>
					<ns2:planFirstYearSum>19079.0</ns2:planFirstYearSum>
					<ns2:planLastYearSum>19079.0</ns2:planLastYearSum>
					<ns2:autPlanYearSum>0</ns2:autPlanYearSum>
				</ns2:sum>
			</ns2:planPaymentIndex>
			<ns2:planPaymentIndex>
				<ns2:name> капитальные вложения в объекты государственной муниципальной собственности всего</ns2:name>
				<ns2:lineCode>2650</ns2:lineCode>
				<ns2:manually>false</ns2:manually>
				<ns2:sum>
					<ns2:financialYearSum>0</ns2:financialYearSum>
					<ns2:planFirstYearSum>0</ns2:planFirstYearSum>
					<ns2:planLastYearSum>0</ns2:planLastYearSum>
					<ns2:autPlanYearSum>0</ns2:autPlanYearSum>
				</ns2:sum>
			</ns2:planPaymentIndex>
			<ns2:planPaymentIndex>
				<ns2:name> в том числе приобретение объектов недвижимого имущества государственными муниципальными учреждения</ns2:name>
				<ns2:lineCode>2651</ns2:lineCode>
				<ns2:manually>false</ns2:manually>
				<ns2:sum>
					<ns2:financialYearSum>0</ns2:financialYearSum>
					<ns2:planFirstYearSum>0</ns2:planFirstYearSum>
					<ns2:planLastYearSum>0</ns2:planLastYearSum>
					<ns2:autPlanYearSum>0</ns2:autPlanYearSum>
				</ns2:sum>
			</ns2:planPaymentIndex>
			<ns2:planPaymentIndex>
				<ns2:name> строительство реконструкция объектов недвижимого имущества государственными муниципальными учреждениями</ns2:name>
				<ns2:lineCode>2652</ns2:lineCode>
				<ns2:manually>false</ns2:manually>
				<ns2:sum>
					<ns2:financialYearSum>0</ns2:financialYearSum>
					<ns2:planFirstYearSum>0</ns2:planFirstYearSum>
					<ns2:planLastYearSum>0</ns2:planLastYearSum>
					<ns2:autPlanYearSum>0</ns2:autPlanYearSum>
				</ns2:sum>
			</ns2:planPaymentIndex>
			<ns2:planPaymentIndex>
				<ns2:name>Выплаты уменьшающие доход всего 8</ns2:name>
				<ns2:lineCode>3000</ns2:lineCode>
				<ns2:manually>false</ns2:manually>
				<ns2:sum>
					<ns2:financialYearSum>0</ns2:financialYearSum>
					<ns2:planFirstYearSum>0</ns2:planFirstYearSum>
					<ns2:planLastYearSum>0</ns2:planLastYearSum>
				</ns2:sum>
			</ns2:planPaymentIndex>
			<ns2:planPaymentIndex>
				<ns2:name> в том числе налог на прибыль 8  </ns2:name>
				<ns2:lineCode>3010</ns2:lineCode>
				<ns2:manually>false</ns2:manually>
				<ns2:sum>
					<ns2:financialYearSum>0</ns2:financialYearSum>
					<ns2:planFirstYearSum>0</ns2:planFirstYearSum>
					<ns2:planLastYearSum>0</ns2:planLastYearSum>
				</ns2:sum>
			</ns2:planPaymentIndex>
			<ns2:planPaymentIndex>
				<ns2:name> налог н адобавленную стоимость 8</ns2:name>
				<ns2:lineCode>3020</ns2:lineCode>
				<ns2:manually>false</ns2:manually>
				<ns2:sum>
					<ns2:financialYearSum>0</ns2:financialYearSum>
					<ns2:planFirstYearSum>0</ns2:planFirstYearSum>
					<ns2:planLastYearSum>0</ns2:planLastYearSum>
				</ns2:sum>
			</ns2:planPaymentIndex>
			<ns2:planPaymentIndex>
				<ns2:name> прочие налоги уменьшающие доход 8</ns2:name>
				<ns2:lineCode>3030</ns2:lineCode>
				<ns2:manually>false</ns2:manually>
				<ns2:sum>
					<ns2:financialYearSum>0</ns2:financialYearSum>
					<ns2:planFirstYearSum>0</ns2:planFirstYearSum>
					<ns2:planLastYearSum>0</ns2:planLastYearSum>
				</ns2:sum>
			</ns2:planPaymentIndex>
			<ns2:planPaymentIndex>
				<ns2:name>Прочие выплаты всего 9</ns2:name>
				<ns2:lineCode>4000</ns2:lineCode>
				<ns2:manually>false</ns2:manually>
				<ns2:sum>
					<ns2:financialYearSum>0</ns2:financialYearSum>
					<ns2:planFirstYearSum>0</ns2:planFirstYearSum>
					<ns2:planLastYearSum>0</ns2:planLastYearSum>
				</ns2:sum>
			</ns2:planPaymentIndex>
			<ns2:planPaymentIndex>
				<ns2:name> из них возврат в бюджет средств субсидии</ns2:name>
				<ns2:lineCode>4010</ns2:lineCode>
				<ns2:manually>false</ns2:manually>
				<ns2:sum>
					<ns2:financialYearSum>0</ns2:financialYearSum>
					<ns2:planFirstYearSum>0</ns2:planFirstYearSum>
					<ns2:planLastYearSum>0</ns2:planLastYearSum>
				</ns2:sum>
			</ns2:planPaymentIndex>
			<ns2:planPaymentTRU>
				<ns2:name>Выплаты на закупку товаров работ услуг всего 11</ns2:name>
				<ns2:lineCode>26000</ns2:lineCode>
				<ns2:manually>false</ns2:manually>
				<ns2:sum>
					<ns2:financialYearSum>10742279.10</ns2:financialYearSum>
					<ns2:planFirstYearSum>7914750.96</ns2:planFirstYearSum>
					<ns2:planLastYearSum>7468050.96</ns2:planLastYearSum>
					<ns2:autPlanYearSum>0</ns2:autPlanYearSum>
				</ns2:sum>
			</ns2:planPaymentTRU>
			<ns2:planPaymentTRU>
				<ns2:name> в том числе по контрактам договорам заключенным до начала текущего финансового года без применения норм Федерального закона от 5 апреля 2013 г N 44ФЗ О контрактной системе в сфере закупок товаров работ услуг для обеспечения государственных и муниципальных нужд Собрание законодательства Российской Федерации 2013 N 14 ст 1652 2018 N 32 ст 5104 далее  Федеральный закон N 44ФЗ и Федерального закона от 18 июля 2011 г N 223ФЗ О закупках товаров  работ услуг отдельными видами юридических лиц Собрание законодательства Российской Федерации 2011 N 30 ст 4571 2018 N 32 ст 5135 далее  Федеральный закон N 223ФЗ 12</ns2:name>
				<ns2:lineCode>26100</ns2:lineCode>
				<ns2:manually>false</ns2:manually>
				<ns2:sum>
					<ns2:financialYearSum>0</ns2:financialYearSum>
					<ns2:planFirstYearSum>0</ns2:planFirstYearSum>
					<ns2:planLastYearSum>0</ns2:planLastYearSum>
					<ns2:autPlanYearSum>0</ns2:autPlanYearSum>
				</ns2:sum>
			</ns2:planPaymentTRU>
			<ns2:planPaymentTRU>
				<ns2:name> по контрактам договорам планируемым к заключению в соответствующем финансовом году без применения норм Федерального закона N 44ФЗ и Федерального закона N 223ФЗ 12</ns2:name>
				<ns2:lineCode>26200</ns2:lineCode>
				<ns2:manually>false</ns2:manually>
				<ns2:sum>
					<ns2:financialYearSum>0</ns2:financialYearSum>
					<ns2:planFirstYearSum>0</ns2:planFirstYearSum>
					<ns2:planLastYearSum>0</ns2:planLastYearSum>
					<ns2:autPlanYearSum>0</ns2:autPlanYearSum>
				</ns2:sum>
			</ns2:planPaymentTRU>
			<ns2:planPaymentTRU>
				<ns2:name> по контрактам договорам заключенным до начала текущего финансового года с учетом требований Федерального закона N 44ФЗ и Федерального закона N 223ФЗ 13</ns2:name>
				<ns2:lineCode>26300</ns2:lineCode>
				<ns2:manually>false</ns2:manually>
				<ns2:sum>
					<ns2:financialYearSum>0</ns2:financialYearSum>
					<ns2:planFirstYearSum>0</ns2:planFirstYearSum>
					<ns2:planLastYearSum>0</ns2:planLastYearSum>
					<ns2:autPlanYearSum>0</ns2:autPlanYearSum>
				</ns2:sum>
			</ns2:planPaymentTRU>
			<ns2:planPaymentTRU>
				<ns2:name> по контрактам договорам планируемым к заключению в соответствующем финансовом году с учетом требований Федерального закона N 44ФЗ и Федерального закона N 223ФЗ 13</ns2:name>
				<ns2:lineCode>26400</ns2:lineCode>
				<ns2:manually>false</ns2:manually>
				<ns2:sum>
					<ns2:financialYearSum>0</ns2:financialYearSum>
					<ns2:planFirstYearSum>0</ns2:planFirstYearSum>
					<ns2:planLastYearSum>0</ns2:planLastYearSum>
					<ns2:autPlanYearSum>0</ns2:autPlanYearSum>
				</ns2:sum>
			</ns2:planPaymentTRU>
			<ns2:planPaymentTRU>
				<ns2:name> в том числе за счет субсидий предоставляемых на финансовое  обеспечение выполнения государственного  муниципального задания</ns2:name>
				<ns2:lineCode>26410</ns2:lineCode>
				<ns2:manually>false</ns2:manually>
				<ns2:sum>
					<ns2:financialYearSum>0</ns2:financialYearSum>
					<ns2:planFirstYearSum>0</ns2:planFirstYearSum>
					<ns2:planLastYearSum>0</ns2:planLastYearSum>
					<ns2:autPlanYearSum>0</ns2:autPlanYearSum>
				</ns2:sum>
			</ns2:planPaymentTRU>
			<ns2:planPaymentTRU>
				<ns2:name> в том числе в соответствии с Федеральным законом N 44ФЗ</ns2:name>
				<ns2:lineCode>26411</ns2:lineCode>
				<ns2:manually>false</ns2:manually>
				<ns2:sum>
					<ns2:financialYearSum>0</ns2:financialYearSum>
					<ns2:planFirstYearSum>0</ns2:planFirstYearSum>
					<ns2:planLastYearSum>0</ns2:planLastYearSum>
					<ns2:autPlanYearSum>0</ns2:autPlanYearSum>
				</ns2:sum>
			</ns2:planPaymentTRU>
			<ns2:planPaymentTRU>
				<ns2:name> в соответствии с Федеральным законом N 223ФЗ 14</ns2:name>
				<ns2:lineCode>26412</ns2:lineCode>
				<ns2:manually>false</ns2:manually>
				<ns2:sum>
					<ns2:financialYearSum>0</ns2:financialYearSum>
					<ns2:planFirstYearSum>0</ns2:planFirstYearSum>
					<ns2:planLastYearSum>0</ns2:planLastYearSum>
					<ns2:autPlanYearSum>0</ns2:autPlanYearSum>
				</ns2:sum>
			</ns2:planPaymentTRU>
			<ns2:planPaymentTRU>
				<ns2:name> за счет субсидий предоставляемых в соответствии с  абзацем вторым пункта 1 статьи 781 Бюджетного  кодекса Российской Федерации</ns2:name>
				<ns2:lineCode>26420</ns2:lineCode>
				<ns2:manually>false</ns2:manually>
				<ns2:sum>
					<ns2:financialYearSum>0</ns2:financialYearSum>
					<ns2:planFirstYearSum>0</ns2:planFirstYearSum>
					<ns2:planLastYearSum>0</ns2:planLastYearSum>
					<ns2:autPlanYearSum>0</ns2:autPlanYearSum>
				</ns2:sum>
			</ns2:planPaymentTRU>
			<ns2:planPaymentTRU>
				<ns2:name> в том числе в соответствии с Федеральным законом N 44ФЗ</ns2:name>
				<ns2:lineCode>26421</ns2:lineCode>
				<ns2:manually>false</ns2:manually>
				<ns2:sum>
					<ns2:financialYearSum>0</ns2:financialYearSum>
					<ns2:planFirstYearSum>0</ns2:planFirstYearSum>
					<ns2:planLastYearSum>0</ns2:planLastYearSum>
					<ns2:autPlanYearSum>0</ns2:autPlanYearSum>
				</ns2:sum>
			</ns2:planPaymentTRU>
			<ns2:planPaymentTRU>
				<ns2:name> в соответствии с Федеральным законом N 223ФЗ 14</ns2:name>
				<ns2:lineCode>26422</ns2:lineCode>
				<ns2:manually>false</ns2:manually>
				<ns2:sum>
					<ns2:financialYearSum>0</ns2:financialYearSum>
					<ns2:planFirstYearSum>0</ns2:planFirstYearSum>
					<ns2:planLastYearSum>0</ns2:planLastYearSum>
					<ns2:autPlanYearSum>0</ns2:autPlanYearSum>
				</ns2:sum>
			</ns2:planPaymentTRU>
			<ns2:planPaymentTRU>
				<ns2:name> за счет субсидий предоставляемых на осуществление  капитальных вложений 15</ns2:name>
				<ns2:lineCode>26430</ns2:lineCode>
				<ns2:manually>false</ns2:manually>
				<ns2:sum>
					<ns2:financialYearSum>0</ns2:financialYearSum>
					<ns2:planFirstYearSum>0</ns2:planFirstYearSum>
					<ns2:planLastYearSum>0</ns2:planLastYearSum>
					<ns2:autPlanYearSum>0</ns2:autPlanYearSum>
				</ns2:sum>
			</ns2:planPaymentTRU>
			<ns2:planPaymentTRU>
				<ns2:name> за счет средств обязательного медицинского  страхования</ns2:name>
				<ns2:lineCode>26440</ns2:lineCode>
				<ns2:manually>false</ns2:manually>
				<ns2:sum>
					<ns2:financialYearSum>0</ns2:financialYearSum>
					<ns2:planFirstYearSum>0</ns2:planFirstYearSum>
					<ns2:planLastYearSum>0</ns2:planLastYearSum>
					<ns2:autPlanYearSum>0</ns2:autPlanYearSum>
				</ns2:sum>
			</ns2:planPaymentTRU>
			<ns2:planPaymentTRU>
				<ns2:name> в том числе в соответствии с Федеральным законом N 44ФЗ</ns2:name>
				<ns2:lineCode>26441</ns2:lineCode>
				<ns2:manually>false</ns2:manually>
				<ns2:sum>
					<ns2:financialYearSum>0</ns2:financialYearSum>
					<ns2:planFirstYearSum>0</ns2:planFirstYearSum>
					<ns2:planLastYearSum>0</ns2:planLastYearSum>
					<ns2:autPlanYearSum>0</ns2:autPlanYearSum>
				</ns2:sum>
			</ns2:planPaymentTRU>
			<ns2:planPaymentTRU>
				<ns2:name> в соответствии с Федеральным законом N 223ФЗ 14</ns2:name>
				<ns2:lineCode>26442</ns2:lineCode>
				<ns2:manually>false</ns2:manually>
				<ns2:sum>
					<ns2:financialYearSum>0</ns2:financialYearSum>
					<ns2:planFirstYearSum>0</ns2:planFirstYearSum>
					<ns2:planLastYearSum>0</ns2:planLastYearSum>
					<ns2:autPlanYearSum>0</ns2:autPlanYearSum>
				</ns2:sum>
			</ns2:planPaymentTRU>
			<ns2:planPaymentTRU>
				<ns2:name> за счет прочих источников финансового обеспечения</ns2:name>
				<ns2:lineCode>26450</ns2:lineCode>
				<ns2:manually>false</ns2:manually>
				<ns2:sum>
					<ns2:financialYearSum>0</ns2:financialYearSum>
					<ns2:planFirstYearSum>0</ns2:planFirstYearSum>
					<ns2:planLastYearSum>0</ns2:planLastYearSum>
					<ns2:autPlanYearSum>0</ns2:autPlanYearSum>
				</ns2:sum>
			</ns2:planPaymentTRU>
			<ns2:planPaymentTRU>
				<ns2:name> в том числе в соответствии с Федеральным законом N 44ФЗ</ns2:name>
				<ns2:lineCode>26451</ns2:lineCode>
				<ns2:manually>false</ns2:manually>
				<ns2:sum>
					<ns2:financialYearSum>0</ns2:financialYearSum>
					<ns2:planFirstYearSum>0</ns2:planFirstYearSum>
					<ns2:planLastYearSum>0</ns2:planLastYearSum>
					<ns2:autPlanYearSum>0</ns2:autPlanYearSum>
				</ns2:sum>
			</ns2:planPaymentTRU>
			<ns2:planPaymentTRU>
				<ns2:name> в соответствии с Федеральным законом N 223ФЗ</ns2:name>
				<ns2:lineCode>26452</ns2:lineCode>
				<ns2:manually>false</ns2:manually>
				<ns2:sum>
					<ns2:financialYearSum>0</ns2:financialYearSum>
					<ns2:planFirstYearSum>0</ns2:planFirstYearSum>
					<ns2:planLastYearSum>0</ns2:planLastYearSum>
					<ns2:autPlanYearSum>0</ns2:autPlanYearSum>
				</ns2:sum>
			</ns2:planPaymentTRU>
			<ns2:planPaymentTRU>
				<ns2:name>Итого по контрактам планируемым к заключению в соответствующем финансовом году в соответствии с Федеральным законом N 44ФЗ по соответствующему году закупки 16</ns2:name>
				<ns2:lineCode>26500</ns2:lineCode>
				<ns2:manually>false</ns2:manually>
				<ns2:sum>
					<ns2:financialYearSum>0</ns2:financialYearSum>
					<ns2:planFirstYearSum>0</ns2:planFirstYearSum>
					<ns2:planLastYearSum>0</ns2:planLastYearSum>
					<ns2:autPlanYearSum>0</ns2:autPlanYearSum>
				</ns2:sum>
			</ns2:planPaymentTRU>
			<ns2:planPaymentTRU>
				<ns2:name> в том числе по году начала закупки</ns2:name>
				<ns2:lineCode>26510</ns2:lineCode>
				<ns2:manually>false</ns2:manually>
				<ns2:sum>
					<ns2:financialYearSum>0</ns2:financialYearSum>
					<ns2:planFirstYearSum>0</ns2:planFirstYearSum>
					<ns2:planLastYearSum>0</ns2:planLastYearSum>
					<ns2:autPlanYearSum>0</ns2:autPlanYearSum>
				</ns2:sum>
			</ns2:planPaymentTRU>
		</ns3:position>
	</ns3:body>
</ns3:financialActivityPlan2020>
